{
  "form_type": "form_122a1",
  "template_filename": "b_122a-1.pdf",
  "template_version": "8777cd40861b6f2b37bdc591a7ea68eb05bdf02841083702887c6d989ed98443",
  "fields": [
    {
      "pdf_field": "Name",
      "type": "text",
      "source": "derived",
      "on_states": [],
      "page": 1,
      "label": "Debtor name",
      "required": true,
      "conditional_on": null,
      "value": null,
      "rule": "full_name",
      "ingest_key": null,
      "binding": null,
      "repeat": null,
      "repeat_capacity": null,
      "row": null,
      "legal_review": false
    },
    {
      "pdf_field": "Bankruptcy District Information",
      "type": "choice",
      "source": "derived",
      "on_states": [],
      "page": 1,
      "label": "Bankruptcy district",
      "required": true,
      "conditional_on": null,
      "value": null,
      "rule": "district_name",
      "ingest_key": null,
      "binding": null,
      "repeat": null,
      "repeat_capacity": null,
      "row": null,
      "legal_review": false
    },
    {
      "pdf_field": "CheckBox2",
      "type": "checkbox",
      "source": "constant",
      "on_states": [],
      "page": 1,
      "label": "Amended filing",
      "required": false,
      "conditional_on": null,
      "value": "",
      "rule": null,
      "ingest_key": null,
      "binding": null,
      "repeat": null,
      "repeat_capacity": null,
      "row": null,
      "legal_review": false
    },
    {
      "pdf_field": "0",
      "type": "text",
      "source": "derived",
      "on_states": [],
      "page": 1,
      "label": "Line 1: Wages, salaries, tips",
      "required": false,
      "conditional_on": null,
      "value": null,
      "rule": "line1_wages",
      "ingest_key": null,
      "binding": null,
      "repeat": null,
      "repeat_capacity": null,
      "row": null,
      "legal_review": false
    },
    {
      "pdf_field": "Quest3",
      "type": "text",
      "source": "derived",
      "on_states": [],
      "page": 1,
      "label": "Line 2: Business income",
      "required": false,
      "conditional_on": null,
      "value": null,
      "rule": "line2_business_income",
      "ingest_key": null,
      "binding": null,
      "repeat": null,
      "repeat_capacity": null,
      "row": null,
      "legal_review": false
    },
    {
      "pdf_field": "Quest4",
      "type": "text",
      "source": "derived",
      "on_states": [],
      "page": 1,
      "label": "Line 3: Real property income",
      "required": false,
      "conditional_on": null,
      "value": null,
      "rule": "line3_real_property_income",
      "ingest_key": null,
      "binding": null,
      "repeat": null,
      "repeat_capacity": null,
      "row": null,
      "legal_review": false
    },
    {
      "pdf_field": "2",
      "type": "text",
      "source": "derived",
      "on_states": [],
      "page": 1,
      "label": "Line 4: Interest, dividends",
      "required": false,
      "conditional_on": null,
      "value": null,
      "rule": "line4_interest_dividends",
      "ingest_key": null,
      "binding": null,
      "repeat": null,
      "repeat_capacity": null,
      "row": null,
      "legal_review": false
    },
    {
      "pdf_field": "Quest5A",
      "type": "text",
      "source": "derived",
      "on_states": [],
      "page": 1,
      "label": "Line 5a: Pension, retirement",
      "required": false,
      "conditional_on": null,
      "value": null,
      "rule": "line5a_pension_retirement",
      "ingest_key": null,
      "binding": null,
      "repeat": null,
      "repeat_capacity": null,
      "row": null,
      "legal_review": false
    },
    {
      "pdf_field": "Quest5B",
      "type": "text",
      "source": "derived",
      "on_states": [],
      "page": 1,
      "label": "Line 5b: Social Security",
      "required": false,
      "conditional_on": null,
      "value": null,
      "rule": "line5b_social_security",
      "ingest_key": null,
      "binding": null,
      "repeat": null,
      "repeat_capacity": null,
      "row": null,
      "legal_review": false
    },
    {
      "pdf_field": "Quest6A",
      "type": "text",
      "source": "derived",
      "on_states": [],
      "page": 1,
      "label": "Line 6a: Unemployment compensation",
      "required": false,
      "conditional_on": null,
      "value": null,
      "rule": "line6a_unemployment",
      "ingest_key": null,
      "binding": null,
      "repeat": null,
      "repeat_capacity": null,
      "row": null,
      "legal_review": false
    },
    {
      "pdf_field": "Quest6B",
      "type": "text",
      "source": "derived",
      "on_states": [],
      "page": 1,
      "label": "Line 6b: Child support, alimony",
      "required": false,
      "conditional_on": null,
      "value": null,
      "rule": "line6b_child_support_alimony",
      "ingest_key": null,
      "binding": null,
      "repeat": null,
      "repeat_capacity": null,
      "row": null,
      "legal_review": false
    },
    {
      "pdf_field": "Quest7",
      "type": "text",
      "source": "derived",
      "on_states": [],
      "page": 1,
      "label": "Line 7: Other income",
      "required": false,
      "conditional_on": null,
      "value": null,
      "rule": "line7_other_income",
      "ingest_key": null,
      "binding": null,
      "repeat": null,
      "repeat_capacity": null,
      "row": null,
      "legal_review": false
    },
    {
      "pdf_field": "Quest8A",
      "type": "text",
      "source": "derived",
      "on_states": [],
      "page": 2,
      "label": "Line 8a: Total gross income",
      "required": false,
      "conditional_on": null,
      "value": null,
      "rule": "line8a_total_gross_income",
      "ingest_key": null,
      "binding": null,
      "repeat": null,
      "repeat_capacity": null,
      "row": null,
      "legal_review": false
    },
    {
      "pdf_field": "Quest9",
      "type": "text",
      "source": "derived",
      "on_states": [],
      "page": 2,
      "label": "Line 9: Household size",
      "required": false,
      "conditional_on": null,
      "value": null,
      "rule": "family_size",
      "ingest_key": null,
      "binding": null,
      "repeat": null,
      "repeat_capacity": null,
      "row": null,
      "legal_review": false
    },
    {
      "pdf_field": "Quest10A",
      "type": "text",
      "source": "derived",
      "on_states": [],
      "page": 2,
      "label": "Line 10a: Deductions",
      "required": false,
      "conditional_on": null,
      "value": null,
      "rule": "line10a_deductions",
      "ingest_key": null,
      "binding": null,
      "repeat": null,
      "repeat_capacity": null,
      "row": null,
      "legal_review": false
    },
    {
      "pdf_field": "Quest10B",
      "type": "text",
      "source": "derived",
      "on_states": [],
      "page": 2,
      "label": "Line 10b: Total deductions",
      "required": false,
      "conditional_on": null,
      "value": null,
      "rule": "line10b_total_deductions",
      "ingest_key": null,
      "binding": null,
      "repeat": null,
      "repeat_capacity": null,
      "row": null,
      "legal_review": false
    },
    {
      "pdf_field": "Quest10C",
      "type": "text",
      "source": "derived",
      "on_states": [],
      "page": 2,
      "label": "Line 10c: Net income",
      "required": false,
      "conditional_on": null,
      "value": null,
      "rule": "line10c_net_income",
      "ingest_key": null,
      "binding": null,
      "repeat": null,
      "repeat_capacity": null,
      "row": null,
      "legal_review": false
    },
    {
      "pdf_field": "Quest11",
      "type": "text",
      "source": "derived",
      "on_states": [],
      "page": 2,
      "label": "Line 11: Annualized income",
      "required": false,
      "conditional_on": null,
      "value": null,
      "rule": "line11_annualized_income",
      "ingest_key": null,
      "binding": null,
      "repeat": null,
      "repeat_capacity": null,
      "row": null,
      "legal_review": false
    },
    {
      "pdf_field": "12B",
      "type": "text",
      "source": "derived",
      "on_states": [],
      "page": 2,
      "label": "Line 12B: Annualized CMI",
      "required": false,
      "conditional_on": null,
      "value": null,
      "rule": "line12b_annualized_cmi",
      "ingest_key": null,
      "binding": null,
      "repeat": null,
      "repeat_capacity": null,
      "row": null,
      "legal_review": false
    },
    {
      "pdf_field": "13A",
      "type": "text",
      "source": "derived",
      "on_states": [],
      "page": 2,
      "label": "Line 13A: State median income",
      "required": false,
      "conditional_on": null,
      "value": null,
      "rule": "line13a_median_income",
      "ingest_key": null,
      "binding": null,
      "repeat": null,
      "repeat_capacity": null,
      "row": null,
      "legal_review": false
    },
    {
      "pdf_field": "13B",
      "type": "text",
      "source": "derived",
      "on_states": [],
      "page": 2,
      "label": "Line 13B: Annualized income",
      "required": false,
      "conditional_on": null,
      "value": null,
      "rule": "line13b_annualized_income",
      "ingest_key": null,
      "binding": null,
      "repeat": null,
      "repeat_capacity": null,
      "row": null,
      "legal_review": false
    },
    {
      "pdf_field": "13C",
      "type": "text",
      "source": "derived",
      "on_states": [],
      "page": 2,
      "label": "Line 13C: Difference",
      "required": false,
      "conditional_on": null,
      "value": null,
      "rule": "line13c_difference",
      "ingest_key": null,
      "binding": null,
      "repeat": null,
      "repeat_capacity": null,
      "row": null,
      "legal_review": false
    },
    {
      "pdf_field": "sig",
      "type": "text",
      "source": "derived",
      "on_states": [],
      "page": 3,
      "label": "Signature of debtor",
      "required": false,
      "conditional_on": null,
      "value": null,
      "rule": "full_name",
      "ingest_key": null,
      "binding": null,
      "repeat": null,
      "repeat_capacity": null,
      "row": null,
      "legal_review": false
    },
    {
      "pdf_field": "Date signed",
      "type": "text",
      "source": "derived",
      "on_states": [],
      "page": 3,
      "label": "Date signed",
      "required": false,
      "conditional_on": null,
      "value": null,
      "rule": "today_iso",
      "ingest_key": null,
      "binding": null,
      "repeat": null,
      "repeat_capacity": null,
      "row": null,
      "legal_review": false
    }
  ]
}
